pass_admin/__init__.py
pass_admin/admin.py
pass_admin/admin_check.py
pass_admin/login_err.py
pass_admin/main.py
pass_admin/r_w_data.py
pass_admin/user.py
test3_pass_admin_Smarv-0.0.1.dist-info/LICENSE
test3_pass_admin_Smarv-0.0.1.dist-info/METADATA
test3_pass_admin_Smarv-0.0.1.dist-info/WHEEL
test3_pass_admin_Smarv-0.0.1.dist-info/top_level.txt
test3_pass_admin_Smarv-0.0.1.dist-info/RECORD
