Metadata-Version: 2.1
Name: test3-pass-admin-Smarv
Version: 0.0.1
Summary: A simple password admin program
Home-page: https://github.com/pypa/sampleproject
Author: Stanislav
Author-email: smarv666@example.com
License: UNKNOWN
Project-URL: Bug Tracker, https://github.com/pypa/sampleproject/issues
Platform: UNKNOWN
Classifier: Programming Language :: Python :: 3
Classifier: License :: OSI Approved :: MIT License
Classifier: Operating System :: OS Independent
Requires-Python: >=3.6
License-File: LICENSE
